pydropbear/__init__.py
pydropbear/__main__.py
pydropbear/dropbearmulti
pydropbear/server.py
pydropbear-0.0.6.dist-info/LICENSE
pydropbear-0.0.6.dist-info/METADATA
pydropbear-0.0.6.dist-info/WHEEL
pydropbear-0.0.6.dist-info/top_level.txt
pydropbear-0.0.6.dist-info/RECORD
